{"base":"http://193.238.158.74","timestamp":1757367459,"total":23,"failures":0,"results":[{"path":"/","status":"PASS","code":200,"size":20408,"time":0.085567},{"path":"/index.html","status":"PASS","code":200,"size":20408,"time":0.075453},{"path":"/js/app.js","status":"PASS","code":200,"size":90463,"time":0.125085},{"path":"/js/jquery.min.js","status":"PASS","code":200,"size":1020,"time":0.069451},{"path":"/js/bootstrap.min.js","status":"PASS","code":200,"size":1292,"time":0.048616},{"path":"/status","status":"PASS","code":200,"size":414654,"time":2.413741},{"path":"/capabilities","status":"PASS","code":200,"size":186,"time":0.050087},{"path":"/connections.json","status":"PASS","code":200,"size":570,"time":0.053947},{"path":"/connections","status":"PASS","code":200,"size":269,"time":0.048932},{"path":"/versions.json","status":"PASS","code":200,"size":589,"time":0.208646},{"path":"/nodedb.json","status":"PASS","code":200,"size":81956,"time":0.119698},{"path":"/airos","status":"PASS","code":200,"size":2,"time":0.057158},{"path":"/traceroute?target=8.8.8.8","status":"PASS","code":200,"size":297,"time":0.115165},{"path":"/olsrd.json?q=links","status":"PASS","code":200,"size":2707,"time":0.175019},{"path":"/olsrd.json?q=neighbors","status":"PASS","code":200,"size":1253,"time":0.167579},{"path":"/olsrd.json?q=routes","status":"PASS","code":200,"size":92019,"time":0.226555},{"path":"/olsrd.json?q=all","status":"PASS","code":200,"size":454176,"time":0.500539},{"path":"/olsrd.json?q=version","status":"PASS","code":200,"size":375,"time":0.142520},{"path":"/olsrd.json?q=interfaces","status":"PASS","code":200,"size":2237,"time":0.154449},{"path":"/olsrd.json?q=topology","status":"PASS","code":200,"size":318733,"time":0.187549},{"path":"/olsrd.json?q=mid","status":"PASS","code":200,"size":8007,"time":0.141766},{"path":"/olsrd.json?q=2hop","status":"PASS","code":200,"size":1772,"time":0.151067},{"path":"/olsrd.json?q=neighbours","status":"PASS","code":200,"size":3862,"time":0.152315}]}